anycast/__init__.py
anycast/py.typed
anycast/api/__init__.py
anycast/api/on_prem_anycast_manager_api.py
anycast/models/__init__.py
anycast/models/anycast_config.py
anycast/models/anycast_config_ref.py
anycast/models/anycast_config_response.py
anycast/models/anycast_version.py
anycast/models/bgp_config.py
anycast/models/bgp_neighbor.py
anycast/models/get_anycast_config_list_response.py
anycast/models/onprem_host.py
anycast/models/onprem_host_ref.py
anycast/models/onprem_host_response.py
anycast/models/ospf_config.py
anycast/models/ospfv3_config.py
anycast/models/protobuf_field_mask.py
anycast/models/service_config.py
anycast/models/service_config_object.py
anycast/models/service_status_code.py
anycast/models/service_status_update_request.py
anycast/test/__init__.py
anycast/test/test_on_prem_anycast_manager_api.py
cloud_discovery/__init__.py
cloud_discovery/py.typed
cloud_discovery/api/__init__.py
cloud_discovery/api/accounts_api.py
cloud_discovery/api/providers_api.py
cloud_discovery/api/sub_accounts_api.py
cloud_discovery/models/__init__.py
cloud_discovery/models/account.py
cloud_discovery/models/account_list_response.py
cloud_discovery/models/additional_config.py
cloud_discovery/models/api_page_info.py
cloud_discovery/models/category.py
cloud_discovery/models/credential_config.py
cloud_discovery/models/credential_preference.py
cloud_discovery/models/destination.py
cloud_discovery/models/destination_config.py
cloud_discovery/models/discovery_config.py
cloud_discovery/models/dns_config.py
cloud_discovery/models/ipam_config.py
cloud_discovery/models/object.py
cloud_discovery/models/object_type.py
cloud_discovery/models/provider_create_response.py
cloud_discovery/models/provider_list_response.py
cloud_discovery/models/provider_read_response.py
cloud_discovery/models/provider_update_response.py
cloud_discovery/models/resource.py
cloud_discovery/models/source_config.py
cloud_discovery/models/sub_account_list_request_v2.py
universal_ddi_python_client-0.1.1.dist-info/METADATA
universal_ddi_python_client-0.1.1.dist-info/WHEEL
universal_ddi_python_client-0.1.1.dist-info/top_level.txt
universal_ddi_python_client-0.1.1.dist-info/RECORD
