Metadata-Version: 2.4
Name: universal-ddi-python-client
Version: 0.1.1
Summary: Python client for the Universal DDI APIs
Home-page: https://github.com/infobloxopen/universal-ddi-python-client
Author: Infoblox
Keywords: Infoblox,Universal,DDI,OpenAPI-Generator
Requires-Dist: urllib3>=2.2.2
Requires-Dist: python-dateutil
Requires-Dist: pydantic>=2
Requires-Dist: typing-extensions>=4.7.1
Dynamic: author
Dynamic: description
Dynamic: description-content-type
Dynamic: home-page
Dynamic: keywords
Dynamic: requires-dist
Dynamic: summary
